wgconf/WireGuardConfiguration.py
wgconf/__init__.py
wgconf/prompt.py
wgconf/utils.py
wgconf-0.4.0.dist-info/entry_points.txt
wgconf-0.4.0.dist-info/LICENSE
wgconf-0.4.0.dist-info/WHEEL
wgconf-0.4.0.dist-info/METADATA
wgconf-0.4.0.dist-info/RECORD
