Metadata-Version: 2.1
Name: wgconf
Version: 0.4.0
Summary: Interactive Wireguard configuration generator
Author: Andy Ta
Author-email: doktorfaustus@live.com
Requires-Python: >=3.8,<4.0
Classifier: Programming Language :: Python :: 3
Classifier: Programming Language :: Python :: 3.10
Classifier: Programming Language :: Python :: 3.8
Classifier: Programming Language :: Python :: 3.9
Requires-Dist: Pillow (==8.3.1)
Requires-Dist: inquirerpy (==0.3.0)
Requires-Dist: pfzy (==0.3.3)
Requires-Dist: prompt-toolkit (==3.0.22)
Requires-Dist: qrcode (==7.2)
Requires-Dist: wcwidth (==0.2.5)
